[{"layer_name": "dense_1", "weight_name": "dense_1_W:0", "offset": 0, "length": 20992, "shape": [82, 256], "type": "float32"}, {"layer_name": "dense_1", "weight_name": "dense_1_b:0", "offset": 83968, "length": 256, "shape": [256], "type": "float32"}, {"layer_name": "dense_2", "weight_name": "dense_2_W:0", "offset": 84992, "length": 65536, "shape": [256, 256], "type": "float32"}, {"layer_name": "dense_2", "weight_name": "dense_2_b:0", "offset": 347136, "length": 256, "shape": [256], "type": "float32"}, {"layer_name": "dense_3", "weight_name": "dense_3_W:0", "offset": 348160, "length": 31232, "shape": [256, 122], "type": "float32"}, {"layer_name": "dense_3", "weight_name": "dense_3_b:0", "offset": 473088, "length": 122, "shape": [122], "type": "float32"}]